package com.b;

public final class j extends Thread
{
  private k b;
  private l c;

  public j(i parami)
  {
  }

  public final k a()
  {
    return this.b;
  }

  public final l b()
  {
    return this.c;
  }

  // ERROR //
  public final void run()
  {
    // Byte code:
    //   0: aload_0
    //   1: getfield 14	com/b/j:a	Lcom/b/i;
    //   4: invokestatic 33	com/b/i:a	(Lcom/b/i;)Ljava/net/Socket;
    //   7: ifnull +447 -> 454
    //   10: aload_0
    //   11: getfield 14	com/b/j:a	Lcom/b/i;
    //   14: invokestatic 33	com/b/i:a	(Lcom/b/i;)Ljava/net/Socket;
    //   17: invokevirtual 38	java/net/Socket:close	()V
    //   20: goto +434 -> 454
    //   23: aload_0
    //   24: getfield 14	com/b/j:a	Lcom/b/i;
    //   27: invokestatic 41	com/b/i:b	(Lcom/b/i;)Lcom/b/q;
    //   30: ifnonnull +9 -> 39
    //   33: iload 6
    //   35: iconst_5
    //   36: if_icmplt +17 -> 53
    //   39: iload 6
    //   41: iconst_5
    //   42: if_icmpne +108 -> 150
    //   45: aload_0
    //   46: getfield 14	com/b/j:a	Lcom/b/i;
    //   49: invokestatic 43	com/b/i:c	(Lcom/b/i;)V
    //   52: return
    //   53: ldc2_w 44
    //   56: invokestatic 49	java/lang/Thread:sleep	(J)V
    //   59: iinc 6 1
    //   62: ldc 51
    //   64: ldc 53
    //   66: invokestatic 59	android/util/Log:d	(Ljava/lang/String;Ljava/lang/String;)I
    //   69: pop
    //   70: goto -47 -> 23
    //   73: astore_1
    //   74: ldc 61
    //   76: ldc 63
    //   78: invokestatic 59	android/util/Log:d	(Ljava/lang/String;Ljava/lang/String;)I
    //   81: pop
    //   82: aload_0
    //   83: getfield 14	com/b/j:a	Lcom/b/i;
    //   86: invokestatic 43	com/b/i:c	(Lcom/b/i;)V
    //   89: invokestatic 68	com/b/p:a	()Lcom/c/b;
    //   92: astore_3
    //   93: new 70	com/c/j
    //   96: dup
    //   97: invokespecial 71	com/c/j:<init>	()V
    //   100: astore 4
    //   102: aload 4
    //   104: aload_3
    //   105: invokevirtual 74	com/c/j:a	(Lcom/c/b;)V
    //   108: aload 4
    //   110: invokevirtual 77	com/c/j:k	()V
    //   113: aload_0
    //   114: getfield 14	com/b/j:a	Lcom/b/i;
    //   117: invokestatic 41	com/b/i:b	(Lcom/b/i;)Lcom/b/q;
    //   120: aload 4
    //   122: invokeinterface 82 2 0
    //   127: aload_1
    //   128: invokevirtual 85	java/io/IOException:printStackTrace	()V
    //   131: ldc 61
    //   133: ldc 87
    //   135: invokestatic 59	android/util/Log:d	(Ljava/lang/String;Ljava/lang/String;)I
    //   138: pop
    //   139: return
    //   140: astore 7
    //   142: aload 7
    //   144: invokevirtual 88	java/lang/InterruptedException:printStackTrace	()V
    //   147: goto -88 -> 59
    //   150: ldc 90
    //   152: putstatic 96	e/c:m	Ljava/lang/String;
    //   155: aload_0
    //   156: getfield 14	com/b/j:a	Lcom/b/i;
    //   159: new 35	java/net/Socket
    //   162: dup
    //   163: invokespecial 97	java/net/Socket:<init>	()V
    //   166: invokestatic 100	com/b/i:a	(Lcom/b/i;Ljava/net/Socket;)V
    //   169: aload_0
    //   170: getfield 14	com/b/j:a	Lcom/b/i;
    //   173: invokestatic 33	com/b/i:a	(Lcom/b/i;)Ljava/net/Socket;
    //   176: new 102	java/net/InetSocketAddress
    //   179: dup
    //   180: aload_0
    //   181: getfield 14	com/b/j:a	Lcom/b/i;
    //   184: invokestatic 105	com/b/i:d	(Lcom/b/i;)Landroid/content/Context;
    //   187: ldc 106
    //   189: invokevirtual 112	android/content/Context:getString	(I)Ljava/lang/String;
    //   192: aload_0
    //   193: getfield 14	com/b/j:a	Lcom/b/i;
    //   196: invokestatic 105	com/b/i:d	(Lcom/b/i;)Landroid/content/Context;
    //   199: invokevirtual 116	android/content/Context:getResources	()Landroid/content/res/Resources;
    //   202: ldc 117
    //   204: invokevirtual 123	android/content/res/Resources:getInteger	(I)I
    //   207: invokespecial 126	java/net/InetSocketAddress:<init>	(Ljava/lang/String;I)V
    //   210: sipush 3000
    //   213: invokevirtual 130	java/net/Socket:connect	(Ljava/net/SocketAddress;I)V
    //   216: aload_0
    //   217: getfield 14	com/b/j:a	Lcom/b/i;
    //   220: invokestatic 33	com/b/i:a	(Lcom/b/i;)Ljava/net/Socket;
    //   223: invokevirtual 134	java/net/Socket:isConnected	()Z
    //   226: ifeq +170 -> 396
    //   229: ldc 61
    //   231: ldc 136
    //   233: invokestatic 59	android/util/Log:d	(Ljava/lang/String;Ljava/lang/String;)I
    //   236: pop
    //   237: aload_0
    //   238: new 138	com/b/k
    //   241: dup
    //   242: aload_0
    //   243: getfield 14	com/b/j:a	Lcom/b/i;
    //   246: invokestatic 105	com/b/i:d	(Lcom/b/i;)Landroid/content/Context;
    //   249: invokespecial 141	com/b/k:<init>	(Landroid/content/Context;)V
    //   252: putfield 20	com/b/j:b	Lcom/b/k;
    //   255: aload_0
    //   256: getfield 20	com/b/j:b	Lcom/b/k;
    //   259: aload_0
    //   260: getfield 14	com/b/j:a	Lcom/b/i;
    //   263: invokestatic 41	com/b/i:b	(Lcom/b/i;)Lcom/b/q;
    //   266: invokevirtual 144	com/b/k:a	(Lcom/b/q;)V
    //   269: aload_0
    //   270: new 146	com/b/l
    //   273: dup
    //   274: aload_0
    //   275: getfield 14	com/b/j:a	Lcom/b/i;
    //   278: invokestatic 150	com/b/i:e	(Lcom/b/i;)Ljava/util/ArrayList;
    //   281: aload_0
    //   282: getfield 14	com/b/j:a	Lcom/b/i;
    //   285: invokestatic 154	com/b/i:f	(Lcom/b/i;)Ljava/util/concurrent/locks/ReentrantLock;
    //   288: aload_0
    //   289: getfield 14	com/b/j:a	Lcom/b/i;
    //   292: invokestatic 105	com/b/i:d	(Lcom/b/i;)Landroid/content/Context;
    //   295: invokespecial 157	com/b/l:<init>	(Ljava/util/ArrayList;Ljava/util/concurrent/locks/ReentrantLock;Landroid/content/Context;)V
    //   298: putfield 23	com/b/j:c	Lcom/b/l;
    //   301: aload_0
    //   302: getfield 23	com/b/j:c	Lcom/b/l;
    //   305: aload_0
    //   306: getfield 14	com/b/j:a	Lcom/b/i;
    //   309: invokestatic 161	com/b/i:g	(Lcom/b/i;)Ljava/lang/String;
    //   312: aload_0
    //   313: getfield 14	com/b/j:a	Lcom/b/i;
    //   316: invokestatic 165	com/b/i:h	(Lcom/b/i;)Lcom/a/f;
    //   319: invokevirtual 168	com/b/l:a	(Ljava/lang/String;Lcom/a/f;)V
    //   322: aload_0
    //   323: getfield 20	com/b/j:b	Lcom/b/k;
    //   326: aload_0
    //   327: getfield 14	com/b/j:a	Lcom/b/i;
    //   330: invokestatic 33	com/b/i:a	(Lcom/b/i;)Ljava/net/Socket;
    //   333: invokevirtual 171	com/b/k:a	(Ljava/net/Socket;)V
    //   336: aload_0
    //   337: getfield 23	com/b/j:c	Lcom/b/l;
    //   340: aload_0
    //   341: getfield 14	com/b/j:a	Lcom/b/i;
    //   344: invokestatic 33	com/b/i:a	(Lcom/b/i;)Ljava/net/Socket;
    //   347: invokevirtual 172	com/b/l:a	(Ljava/net/Socket;)V
    //   350: aload_0
    //   351: getfield 20	com/b/j:b	Lcom/b/k;
    //   354: invokevirtual 175	com/b/k:start	()V
    //   357: aload_0
    //   358: getfield 23	com/b/j:c	Lcom/b/l;
    //   361: invokevirtual 176	com/b/l:start	()V
    //   364: new 70	com/c/j
    //   367: dup
    //   368: invokespecial 71	com/c/j:<init>	()V
    //   371: astore 13
    //   373: invokestatic 180	e/a:a	()V
    //   376: aload 13
    //   378: invokestatic 182	e/a:b	()Lcom/c/b;
    //   381: invokevirtual 74	com/c/j:a	(Lcom/c/b;)V
    //   384: aload_0
    //   385: getfield 23	com/b/j:c	Lcom/b/l;
    //   388: aload 13
    //   390: invokevirtual 183	com/b/l:a	(Lcom/c/j;)V
    //   393: goto -262 -> 131
    //   396: ldc 61
    //   398: ldc 185
    //   400: invokestatic 59	android/util/Log:d	(Ljava/lang/String;Ljava/lang/String;)I
    //   403: pop
    //   404: aload_0
    //   405: getfield 14	com/b/j:a	Lcom/b/i;
    //   408: invokestatic 43	com/b/i:c	(Lcom/b/i;)V
    //   411: invokestatic 68	com/b/p:a	()Lcom/c/b;
    //   414: astore 10
    //   416: new 70	com/c/j
    //   419: dup
    //   420: invokespecial 71	com/c/j:<init>	()V
    //   423: astore 11
    //   425: aload 11
    //   427: aload 10
    //   429: invokevirtual 74	com/c/j:a	(Lcom/c/b;)V
    //   432: aload 11
    //   434: invokevirtual 77	com/c/j:k	()V
    //   437: aload_0
    //   438: getfield 14	com/b/j:a	Lcom/b/i;
    //   441: invokestatic 41	com/b/i:b	(Lcom/b/i;)Lcom/b/q;
    //   444: aload 11
    //   446: invokeinterface 82 2 0
    //   451: goto -320 -> 131
    //   454: iconst_0
    //   455: istore 6
    //   457: goto -434 -> 23
    //
    // Exception table:
    //   from	to	target	type
    //   0	20	73	java/io/IOException
    //   23	33	73	java/io/IOException
    //   45	52	73	java/io/IOException
    //   53	59	73	java/io/IOException
    //   62	70	73	java/io/IOException
    //   142	147	73	java/io/IOException
    //   150	393	73	java/io/IOException
    //   396	451	73	java/io/IOException
    //   53	59	140	java/lang/InterruptedException
  }
}

/* Location:           /Users/mdp/Downloads/iMessage/classes-dex2jar.jar
 * Qualified Name:     com.b.j
 * JD-Core Version:    0.6.2
 */